celery_redis_cluster_backend/__init__.py
celery_redis_cluster_backend/backend.py
celery_redis_cluster-0.2.1.dist-info/LICENSE
celery_redis_cluster-0.2.1.dist-info/METADATA
celery_redis_cluster-0.2.1.dist-info/WHEEL
celery_redis_cluster-0.2.1.dist-info/entry_points.txt
celery_redis_cluster-0.2.1.dist-info/top_level.txt
celery_redis_cluster-0.2.1.dist-info/RECORD
